{
  "products": [
    {
      "id":1,
      "popularity": "Best Seller",
      "image": "https://assets.specialized.com/i/specialized/96223-30_DIVERGE-STR-EXPERT-BLK-DMNDDST_HERO?bg=rgb(241,241,241)&w=1600&h=900&fmt=auto",
      "name": "Tarmac SL7 Comp - Rival eTap AXS",
      "price": "$5,500",
      "mrp": "$7,500",
      "image1": "https://assets.specialized.com/i/specialized/96223-30_DIVERGE-STR-EXPERT-BLK-DMNDDST_FDSQ?bg=rgb(241,241,241)&w=1600&h=900&fmt=auto",
      "image2": "https://assets.specialized.com/i/specialized/96223-30_DIVERGE-STR-EXPERT-BLK-DMNDDST_D1-POV?bg=rgb(241,241,241)&w=1600&h=900&fmt=auto",
      "image3": "https://assets.specialized.com/i/specialized/96223-30_DIVERGE-STR-EXPERT-BLK-DMNDDST_D2-BAR?bg=rgb(241,241,241)&w=1600&h=900&fmt=auto",
      "image4": "https://assets.specialized.com/i/specialized/96223-30_DIVERGE-STR-EXPERT-BLK-DMNDDST_D4-STTT?bg=rgb(241,241,241)&w=1600&h=900&fmt=auto",
      "image5": "https://assets.specialized.com/i/specialized/96223-30_DIVERGE-STR-EXPERT-BLK-DMNDDST_D3-HT?bg=rgb(241,241,241)&w=1600&h=900&fmt=auto",
      "imgae6": "https://assets.specialized.com/i/specialized/96223-30_DIVERGE-STR-EXPERT-BLK-DMNDDST_RDSQ?bg=rgb(241,241,241)&w=1600&h=900&fmt=auto"

    },
    {
      "id":2,
      "popularity": "Best Seller",
      "image": "https://www.specialized.com/us/en/diverge-comp-carbon/p/199965?color=322129-199965",
      "name": "Diverge Comp Carbon",
      "price": "$4,200",
      "mrp": ""
    },
    {
      "id":3,
      "popularity": "Best Seller",
      "image": "https://www.specialized.com/us/en/diverge-sport-carbon/p/199964?color=322115-199964",
      "name": "Diverge Sport Carbon",
      "price": "$3,500",
      "mrp": ""
    },
    {
      "id":4,
      "popularity": "Best Seller",
      "image": "https://www.specialized.com/us/en/roubaix-sport/p/199910?color=321758-199910",
      "name": "Roubaix Sport",
      "price": "$3,500",
      "mrp": ""
    },
    {
      "id":5,
      "popularity": "Best Seller",
      "image": "https://www.specialized.com/us/en/diverge-elite-e5/p/199974?color=322134-199974",
      "name": "Diverge Elite E5",
      "price": "$2,000",
      "mrp": ""
    },
    {
      "popularity": "Best Seller",
      "image": "https://www.specialized.com/us/en/diverge-e5/p/199973?color=322113-199973",
      "name": "Diverge E5",
      "price": "$1,300",
      "mrp": ""
    },
    {
      "id":6,
      "popularity": "",
      "image": "https://www.specialized.com/us/en/s-works-crux/p/205810?color=336182-205810",
      "name": "S-Works Crux",
      "price": "$12,250",
      "mrp": ""
    },
    {
      "id":7,
      "popularity": "",
      "image": "https://www.specialized.com/us/en/s-works-epic/p/205828?color=336304-205828",
      "name": "S-Works Epic",
      "price": "$12,000",
      "mrp": ""
    },
    {
      "id":8,
      "popularity": "New",
      "image": "https://www.specialized.com/us/en/s-works-epic-evo-ltd/p/218876?color=356880-218876",
      "name": "S-Works Epic EVO LTD",
      "price": "$11,000",
      "mrp": ""
    },
    {
      "popularity": "New",
      "image": "https://www.specialized.com/us/en/s-works-stumpjumper/p/200524?color=336222-200524",
      "name": "S-Works Stumpjumper",
      "price": "$11,000",
      "mrp": ""
    },
    {
      "id":9,
      "popularity": "New",
      "image": "https://www.specialized.com/us/en/s-works-epic-ltd/p/218875?color=356862-218875",
      "name": "S-Works Epic LTD",
      "price": "$11,000",
      "mrp": ""
    },
    {
      "id":10,
      "popularity": "New",
      "image": "https://www.specialized.com/us/en/epic-world-cup-pro/p/206076?color=336719-206076",
      "name": "Epic World Cup Pro",
      "price": "$9,000",
      "mrp": ""
    },
    {
      "id":11,
      "popularity": "",
      "image": "https://www.specialized.com/us/en/stumpjumper-evo-ltd/p/218302?color=352720-218302",
      "name": "Stumpjumper EVO LTD",
      "price": "$6,300",
      "mrp": ""
    },
    {
      "id":12,
      "popularity": "",
      "image": "https://www.specialized.com/us/en/crux-expert/p/205812?color=336168-205812",
      "name": "Crux Expert",
      "price": "$6,200",
      "mrp": ""
    },
    {
      "popularity": "New",
      "image": "https://www.specialized.com/us/en/tarmac-sl7-comp--shimano-105-di2/p/216925?color=349979-216925",
      "name": "Tarmac SL7 Comp -Shimano 105 Di2",
      "price": "$5,500",
      "mrp": ""
    },
    {
      "popularity": "",
      "image": "https://www.specialized.com/us/en/crux-comp/p/205813?color=336162-205813",
      "name": "Crux Comp",
      "price": "$4,200",
      "mrp": ""
    },
    {
      "popularity": "",
      "image": "https://www.specialized.com/us/en/diverge-sport-carbon/p/217055?color=350266-217055",
      "name": "Diverge Sport Carbon",
      "price": "$3,500",
      "mrp": ""
    },
    {
      "popularity": "New",
      "image": "https://www.specialized.com/us/en/sirrus-x-5-0/p/200214?color=322033-200214",
      "name": "Sirrus X 5.0",
      "price": "$2,250",
      "mrp": ""
    },
    {
      "popularity": "",
      "image": "https://www.specialized.com/us/en/s-works-tarmac-sl7---shimano-dura-ace-di2/p/199463?color=321621-199463",
      "name": "S-Works Tarmac SL7 - Shimano Dura-Ace Di2",
      "price": "$14,250",
      "mrp": ""
    },
    {
      "popularity": "Best Seller",
      "image": "https://www.specialized.com/us/en/tarmac-sl7-pro---sram-force-etap-axs/p/199466?color=321605-199466",
      "name": "Tarmac SL7 Pro - SRAM Force eTap AXS",
      "price": "$9,000",
      "mrp": ""
    },
    {
      "popularity": "",
      "image": "https://www.specialized.com/us/en/epic-pro/p/205827?color=336305-205827",
      "name": "Epic Pro",
      "price": "$9,000",
      "mrp": ""
    },
    {
      "popularity": "",
      "image": "https://www.specialized.com/us/en/diverge-str-pro/p/200577?color=335116-200577",
      "name": "Diverge STR Pro",
      "price": "$8,700",
      "mrp": ""
    },
    {
      "popularity": "",
      "image": "https://www.specialized.com/us/en/aethos-pro---sram-force-etap-axs/p/199441?color=321745-199441",
      "name": "Aethos Pro - SRAM Force eTap AXS",
      "price": "$8,700",
      "mrp": ""
    },
    {
      "popularity": "",
      "image": "https://www.specialized.com/us/en/tarmac-sl7-expert/p/199467?color=321622-199467",
      "name": "Tarmac SL7 Expert",
      "price": "$8,300",
      "mrp": ""
    },
    {
      "popularity": "",
      "image": "https://www.specialized.com/us/en/diverge-pro-carbon/p/199967?color=322128-199967",
      "name": "Diverge Pro Carbon",
      "price": "$8,200",
      "mrp": ""
    },
    {
      "popularity": "Best Seller",
      "image": "https://www.specialized.com/us/en/aethos-expert/p/199442?color=321747-199442",
      "name": "Aethos Expert",
      "price": "$8,000",
      "mrp": ""
    },
    {
      "popularity": "Best Seller",
      "image": "https://www.specialized.com/us/en/diverge-str-expert/p/200578?color=335135-200578",
      "name": "Diverge STR Expert",
      "price": "$6,700",
      "mrp": ""
    },
    {
      "popularity": "",
      "image": "https://www.specialized.com/us/en/crux-expert/p/199961?color=322120-199961",
      "name": "Crux Expert",
      "price": "$6,200",
      "mrp": ""
    },
    {
      "popularity": "",
      "image": "https://www.specialized.com/us/en/diverge-expert-carbon/p/205815?color=336160-205815",
      "name": "Diverge Expert Carbon",
      "price": "$6,200",
      "mrp": ""
    },
    {
      "popularity": "",
      "image": "https://www.specialized.com/us/en/enduro-comp/p/200513?color=336307-200513",
      "name": "Enduro Comp",
      "price": "$5,500",
      "mrp": ""
    },
    {
      "popularity": "",
      "image": "https://www.specialized.com/us/en/aethos-comp---rival-etap-axs/p/199444?color=321404-199444",
      "name": "Aethos Comp - Rival eTap AXS",
      "price": "$5,200",
      "mrp": ""
    },
    {
      "popularity": "",
      "image": "https://www.specialized.com/us/en/stumpjumper-comp/p/199786?color=320401-199786",
      "name": "Stumpjumper Comp",
      "price": "$5,000",
      "mrp": ""
    },
    {
      "popularity": "",
      "image": "https://www.specialized.com/us/en/epic-evo-comp/p/199655?color=319933-199655",
      "name": "Epic EVO Comp",
      "price": "$4,750",
      "mrp": ""
    },
    {
      "popularity": "",
      "image": "https://www.specialized.com/us/en/stumpjumper-evo-comp-alloy/p/199210?color=318400-199210",
      "name": "Stumpjumper EVO Comp Alloy",
      "price": "$4,400",
      "mrp": ""
    },
    {
      "popularity": "",
      "image": "https://www.specialized.com/us/en/epic-evo/p/205807?color=349303-205807",
      "name": "Epic EVO",
      "price": "$4,000",
      "mrp": ""
    },
    {
      "popularity": "",
      "image": "https://www.specialized.com/us/en/stumpjumper-comp-alloy/p/199785?color=320379-199785",
      "name": "Stumpjumper Comp Alloy",
      "price": "$4,000",
      "mrp": ""
    },
    {
      "popularity": "",
      "image": "https://www.specialized.com/us/en/crossroads-2-0/p/200217?color=322020-200217",
      "name": "Crossroads 2.0",
      "price": "$775",
      "mrp": ""
    },
    {
      "popularity": "",
      "image": "https://www.specialized.com/us/en/sirrus-x-2-0/p/216898?color=350195-216898",
      "name": "Sirrus X 2.0",
      "price": "$649.99",
      "mrp": "$775"
    },
    {
      "popularity": "Best Seller",
      "image": "https://www.specialized.com/us/en/epic-evo-pro/p/205803?color=336284-205803",
      "name": "Epic EVO Pro",
      "price": "$8,499.99",
      "mrp": "$8,900"
    },
    {
      "popularity": "Best Seller",
      "image": "https://www.specialized.com/us/en/epic-evo-expert/p/205805?color=336306-205805",
      "name": "Epic EVO Expert",
      "price": "$6,499.99",
      "mrp": "$7,000"
    },
    {
      "popularity": "Best Seller",
      "image": "https://www.specialized.com/us/en/stumpjumper-evo-pro/p/200533?color=336229-200533",
      "name": "Stumpjumper EVO Pro",
      "price": "$6,374.99",
      "mrp": "$8,600"
    },
    {
      "popularity": "Best Seller",
      "image": "https://www.specialized.com/us/en/stumpjumper-evo-expert/p/200531?color=349346-200531",
      "name": "Stumpjumper EVO Expert",
      "price": "$4,999.99",
      "mrp": "$6,500"
    },
    {
      "popularity": "Best Seller",
      "image": "https://www.specialized.com/us/en/stumpjumper-expert/p/199757?color=320323-199757",
      "name": "Stumpjumper Expert",
      "price": "$4,649.99",
      "mrp": "$6,200"
    },
    {
      "popularity": "Best Seller",
      "image": "https://www.specialized.com/us/en/stumpjumper-evo-expert-rs/p/200366?color=322760-200366",
      "name": "Stumpjumper EVO Expert RS",
      "price": "$4,399.99",
      "mrp": "$6,000"
    },
    {
      "popularity": "Best Seller",
      "image": "https://www.specialized.com/us/en/stumpjumper-evo-comp/p/200528?color=336208-200528",
      "name": "Stumpjumper EVO Comp",
      "price": "$3,749.99",
      "mrp": "$5,400"
    },
    {
      "popularity": "Best Seller",
      "image": "https://www.specialized.com/us/en/stumpjumper-evo-comp/p/199749?color=320261-199749",
      "name": "Stumpjumper EVO Comp",
      "price": "$3,749.99",
      "mrp": "$5,400"
    },
    {
      "popularity": "Best Seller",
      "image": "https://www.specialized.com/us/en/stumpjumper-alloy/p/199784?color=320391-199784",
      "name": "Stumpjumper Alloy",
      "price": "$2,099.99",
      "mrp": "$2,800"
    },
    {
      "popularity": "Best Seller",
      "image": "https://www.specialized.com/us/en/sirrus-x-4-0/p/200213?color=322036-200213",
      "name": "Sirrus X 4.0",
      "price": "$1,279.99",
      "mrp": "$1,600"
    },
    {
      "popularity": "Best Seller",
      "image": "https://www.specialized.com/us/en/fuse-27-5/p/199942?color=321203-199942",
      "name": "Fuse 27.5",
      "price": "$1,099.99",
      "mrp": "$1,500"
    },
    {
      "popularity": "Best Seller",
      "image": "https://www.specialized.com/us/en/rockhopper-expert-29/p/199569?color=319662-199569",
      "name": "Rockhopper Expert 29",
      "price": "$999.99",
      "mrp": "$1,400"
    },
    {
      "popularity": "",
      "image": "https://www.specialized.com/us/en/rockhopper-expert-27-5/p/199570?color=319883-199570",
      "name": "Rockhopper Expert 27.5",
      "price": "$999.99",
      "mrp": "$1,400"
    },
    {
      "popularity": "",
      "image": "https://www.specialized.com/us/en/sirrus-3-0/p/200208?color=322025-200208",
      "name": "Sirrus 3.0",
      "price": "$949.99",
      "mrp": "$1,200"
    },
    {
      "popularity": "",
      "image": "https://www.specialized.com/us/en/roll-3-0/p/216878?color=349786-216878",
      "name": "Roll 3.0",
      "price": "$824.99",
      "mrp": "$1,100"
    },
    {
      "popularity": "",
      "image": "https://www.specialized.com/us/en/roll-3-0-low-entry/p/216879?color=349803-216879",
      "name": "Roll 3.0 Low Entry",
      "price": "$824.99",
      "mrp": "$1,100"
    },
    {
      "popularity": "Best Seller",
      "image": "https://www.specialized.com/us/en/rockhopper-comp-29/p/199585?color=319886-199585",
      "name": "Rockhopper Comp 29",
      "price": "$764.99",
      "mrp": "$950"
    },
    {
      "popularity": "",
      "image": "https://www.specialized.com/us/en/rockhopper-comp-27-5/p/199587?color=319790-199587",
      "name": "Rockhopper Comp 27.5",
      "price": "$764.99",
      "mrp": "$950"
    },
    {
      "popularity": "",
      "image": "https://www.specialized.com/us/en/riprock-24/p/216867?color=349475-216867",
      "name": "Riprock 24",
      "price": "$649.99",
      "mrp": "$700"
    },
    {
      "popularity": "",
      "image": "https://www.specialized.com/us/en/sirrus-2-0/p/216886?color=350188-216886",
      "name": "Sirrus 2.0",
      "price": "$649.99",
      "mrp": "$775"
    },
    {
      "popularity": "Best Seller",
      "image": "https://www.specialized.com/us/en/sirrus-x-2-0/p/200210?color=322038-200210",
      "name": "Sirrus X 2.0",
      "price": "$619.99",
      "mrp": "$775"
    },
    {
      "popularity": "",
      "image": "https://www.specialized.com/us/en/sirrus-2-0/p/200206?color=322050-200206",
      "name": "Sirrus 2.0",
      "price": "$619.99",
      "mrp": "$775"
    },
    {
      "popularity": "",
      "image": "https://www.specialized.com/us/en/roll-2-0/p/216876?color=349801-216876",
      "name": "Roll 2.0",
      "price": "$599.99",
      "mrp": "$800"
    },
    {
      "popularity": "",
      "image": "https://www.specialized.com/us/en/roll-2-0-low-entry/p/216877?color=349783-216877",
      "name": "Roll 2.0 Low Entry",
      "price": "$599.99",
      "mrp": "$800"
    },
    {
      "popularity": "Best Seller",
      "image": "https://www.specialized.com/us/en/rockhopper-sport-29/p/199575?color=319799-199575",
      "name": "Rockhopper Sport 29",
      "price": "$579.99",
      "mrp": "$750"
    },
    {
      "popularity": "",
      "image": "https://www.specialized.com/us/en/rockhopper-sport-27-5/p/199577?color=319812-199577",
      "name": "Rockhopper Sport 27.5",
      "price": "$579.99",
      "mrp": "$750"
    },
    {
      "popularity": "",
      "image": "https://www.specialized.com/us/en/sirrus-1-0/p/200205?color=322028-200205",
      "name": "Sirrus 1.0",
      "price": "$519.99",
      "mrp": "$650"
    },
    {
      "popularity": "Best Seller",
      "image": "https://www.specialized.com/us/en/rockhopper-29/p/199589?color=319848-199589",
      "name": "Rockhopper 29",
      "price": "$499.99",
      "mrp": "$650"
    },
    {
      "popularity": "Best Seller",
      "image": "https://www.specialized.com/us/en/rockhopper-27-5/p/199591?color=319889-199591",
      "name": "Rockhopper 27.5",
      "price": "$499.99",
      "mrp": "$650"
    },
    {
      "popularity": "",
      "image": "https://www.specialized.com/us/en/hotwalk-carbon/p/200221?color=322068-200221",
      "name": "Hotwalk Carbon",
      "price": "$499.99",
      "mrp": "$1,000"
    },
    {
      "popularity": "",
      "image": "https://www.specialized.com/us/en/jett-24/p/186958?color=302621-186958",
      "name": "Jett 24",
      "price": "$474.99",
      "mrp": "$550"
    },
    {
      "popularity": "",
      "image": "https://www.specialized.com/us/en/jett-20/p/186956?color=302622-186956",
      "name": "Jett 20",
      "price": "$399.99",
      "mrp": "$500"
    },
    {
      "popularity": "",
      "image": "https://www.specialized.com/us/en/riprock-coaster-20/p/200230?color=322153-200230",
      "name": "Riprock Coaster 20",
      "price": "$299.99",
      "mrp": "$325"
    },
    {
      "popularity": "",
      "image": "https://www.specialized.com/us/en/jett-16-single-speed/p/216938?color=349730-216938",
      "name": "Jett 16 Single Speed",
      "price": "$274.99",
      "mrp": "$400"
    },
    {
      "popularity": "",
      "image": "https://www.specialized.com/us/en/riprock-coaster-16/p/200228?color=322146-200228",
      "name": "Riprock Coaster 16",
      "price": "$249.99",
      "mrp": "$300"
    },
    {
      "popularity": "",
      "image": "https://www.specialized.com/us/en/s-works-epic-frameset/p/205829?color=349301-205829",
      "name": "S-Works Epic Frameset",
      "price": "$5,499.99",
      "mrp": "$6,000"
    },
    {
      "popularity": "",
      "image": "https://www.specialized.com/us/en/sirrus-x-3-0/p/216902?color=350193-216902",
      "name": "Sirrus X 3.0",
      "price": "$999.99",
      "mrp": "$1,200"
    },
    {
      "popularity": "",
      "image": "https://www.specialized.com/us/en/sirrus-2-0-step-through/p/216885?color=356241-216885",
      "name": "Sirrus 2.0 Step-Through",
      "price": "$649.99",
      "mrp": "$775"
    },
    {
      "popularity": "Best Seller",
      "image": "https://www.specialized.com/us/en/s-works-epic-evo/p/205802?color=336285-205802",
      "name": "S-Works Epic EVO",
      "price": "$11,999.99",
      "mrp": "$13,000"
    },
    {
      "popularity": "",
      "image": "https://www.specialized.com/us/en/s-works-epic-evo-rs/p/205610?color=335500-205610",
      "name": "S-Works Epic EVO RS",
      "price": "$11,999.99",
      "mrp": "$13,000"
    },
    {
      "popularity": "",
      "image": "https://www.specialized.com/us/en/s-works-stumpjumper-ltd/p/200365?color=322742-200365",
      "name": "S-Works Stumpjumper LTD",
      "price": "$8,924.99",
      "mrp": "$11,500"
    },
    {
      "popularity": "",
      "image": "https://www.specialized.com/us/en/s-works-stumpjumper-evo/p/200534?color=336226-200534",
      "name": "S-Works Stumpjumper EVO",
      "price": "$8,799.99",
      "mrp": "$11,500"
    },
    {
      "popularity": "",
      "image": "https://www.specialized.com/us/en/stumpjumper-evo-pro/p/199752?color=320262-199752",
      "name": "Stumpjumper EVO Pro",
      "price": "$6,374.99",
      "mrp": "$8,600"
    },
    {
      "popularity": "",
      "image": "https://www.specialized.com/us/en/enduro-expert/p/200514?color=336308-200514",
      "name": "Enduro Expert",
      "price": "$6,299.99",
      "mrp": "$7,000"
    },
    {
      "popularity": "Best Seller",
      "image": "https://www.specialized.com/us/en/stumpjumper-pro/p/199758?color=320322-199758",
      "name": "Stumpjumper Pro",
      "price": "$6,149.99",
      "mrp": "$8,200"
    },
    {
      "popularity": "",
      "image": "https://www.specialized.com/us/en/enduro-expert/p/199762?color=320381-199762",
      "name": "Enduro Expert",
      "price": "$5,799.99",
      "mrp": "$6,600"
    },
    {
      "popularity": "",
      "image": "https://www.specialized.com/us/en/stumpjumper-evo-expert/p/199751?color=320282-199751",
      "name": "Stumpjumper EVO Expert",
      "price": "$4,999.99",
      "mrp": "$6,300"
    },
    {
      "popularity": "",
      "image": "https://www.specialized.com/us/en/enduro-comp/p/199761?color=320372-199761",
      "name": "Enduro Comp",
      "price": "$4,999.99",
      "mrp": "$5,400"
    },
    {
      "popularity": "",
      "image": "https://www.specialized.com/us/en/stumpjumper-evo-elite-alloy/p/199211?color=318420-199211",
      "name": "Stumpjumper EVO Elite Alloy",
      "price": "$4,799.99",
      "mrp": "$6,100"
    },
    {
      "popularity": "",
      "image": "https://www.specialized.com/us/en/s-works-stumpjumper-evo-frameset/p/200535?color=336209-200535",
      "name": "S-Works Stumpjumper EVO Frameset",
      "price": "$3,199.99",
      "mrp": "$3,400"
    },
    {
      "popularity": "",
      "image": "https://www.specialized.com/us/en/stumpjumper-evo-frameset/p/200532?color=336207-200532",
      "name": "Stumpjumper EVO Frameset",
      "price": "$2,799.99",
      "mrp": "$2,900"
    },
    {
      "popularity": "",
      "image": "https://www.specialized.com/us/en/sirrus-4-0/p/200225?color=322547-200225",
      "name": "Sirrus 4.0",
      "price": "$1,279.99",
      "mrp": "$1,600"
    },
    {
      "popularity": "",
      "image": "https://www.specialized.com/us/en/riprock-expert-24/p/189826?color=318899-189826",
      "name": "Riprock Expert 24",
      "price": "$1,199.99",
      "mrp": "$1,500"
    },
    {
      "popularity": "",
      "image": "https://www.specialized.com/us/en/sirrus-x-3-0/p/200212?color=322053-200212",
      "name": "Sirrus X 3.0",
      "price": "$999.99",
      "mrp": "$1,200"
    },
    {
      "popularity": "",
      "image": "https://www.specialized.com/us/en/sirrus-3-0-step-through/p/174695?color=298952-174695",
      "name": "Sirrus 3.0 Step Through",
      "price": "$949.99",
      "mrp": "$1,200"
    },
    {
      "popularity": "",
      "image": "https://www.specialized.com/us/en/sirrus-2-0-step-through/p/200207?color=322046-200207",
      "name": "Sirrus 2.0 Step-Through",
      "price": "$619.99",
      "mrp": "$775"
    },
    {
      "popularity": "",
      "image": "https://www.specialized.com/us/en/riprock-20/p/217050?color=350202-217050",
      "name": "Riprock 20",
      "price": "$599.99",
      "mrp": "$650"
    },
    {
      "popularity": "",
      "image": "https://www.specialized.com/us/en/sirrus-1-0/p/218445?color=354100-218445",
      "name": "Sirrus 1.0",
      "price": "$549.99",
      "mrp": "$650"
    },
    {
      "popularity": "",
      "image": "https://www.specialized.com/us/en/rockhopper-26/p/199592?color=319851-199592",
      "name": "Rockhopper 26",
      "price": "$499.99",
      "mrp": "$650"
    },
    {
      "popularity": "",
      "image": "https://www.specialized.com/us/en/jett-20-single-speed/p/216864?color=349766-216864",
      "name": "Jett 20 Single Speed",
      "price": "$324.99",
      "mrp": "$425"
    },
    {
      "popularity": "",
      "image": "https://www.specialized.com/us/en/riprock-coaster-12/p/200226?color=322162-200226",
      "name": "Riprock Coaster 12",
      "price": "$234.99",
      "mrp": "$275"
    },
    {
      "popularity": "",
      "image": "https://www.specialized.com/us/en/hotwalk/p/200222?color=322071-200222",
      "name": "Hotwalk",
      "price": "$199.99",
      "mrp": "$225"
    },
    {
      "popularity": "",
      "image": "https://www.specialized.com/us/en/s-works-enduro-frameset/p/200517?color=336310-200517",
      "name": "S-Works Enduro Frameset",
      "price": "$2,999.99",
      "mrp": "$3,400"
    },
    {
      "popularity": "",
      "image": "https://www.specialized.com/us/en/s-works-epic-evo/p/199659?color=319930-199659",
      "name": "S-Works Epic EVO",
      "price": "$11,999.99",
      "mrp": "$13,000"
    },
    {
      "popularity": "",
      "image": "https://www.specialized.com/us/en/s-works-stumpjumper/p/199759?color=320341-199759",
      "name": "S-Works Stumpjumper",
      "price": "$9,999.99",
      "mrp": "$11,000"
    },
    {
      "popularity": "",
      "image": "https://www.specialized.com/us/en/s-works-stumpjumper-evo/p/199753?color=320263-199753",
      "name": "S-Works Stumpjumper EVO",
      "price": "$8,624.99",
      "mrp": "$11,500"
    },
    {
      "popularity": "",
      "image": "https://www.specialized.com/us/en/epic-evo-pro/p/199657?color=319952-199657",
      "name": "Epic EVO Pro",
      "price": "$7,999.99",
      "mrp": "$8,800"
    },
    {
      "popularity": "",
      "image": "https://www.specialized.com/us/en/epic-evo-expert/p/199656?color=319953-199656",
      "name": "Epic EVO Expert",
      "price": "$5,999.99",
      "mrp": "$6,800"
    },
    {
      "popularity": "",
      "image": "https://www.specialized.com/us/en/epic-expert/p/199645?color=319948-199645",
      "name": "Epic Expert",
      "price": "$5,999.99",
      "mrp": "$6,300"
    },
    {
      "popularity": "Coming Soon",
      "image": "https://www.specialized.com/us/en/epic-evo-pro-ltd/p/218878?color=356863-218878",
      "name": "Epic EVO Pro LTD",
      "price": "$8,500",
      "mrp": ""
    },
    {
      "popularity": "Coming Soon",
      "image": "https://www.specialized.com/us/en/epic-pro-ltd/p/218877?color=356881-218877",
      "name": "Epic Pro LTD",
      "price": "$8,500",
      "mrp": ""
    },
    {
      "popularity": "Coming Soon",
      "image": "https://www.specialized.com/us/en/stumpjumper-pro/p/200523?color=336224-200523",
      "name": "Stumpjumper Pro",
      "price": "$8,500",
      "mrp": ""
    },
    {
      "popularity": "Coming Soon",
      "image": "https://www.specialized.com/us/en/sirrus-6-0/p/200224?color=322587-200224",
      "name": "Sirrus 6.0",
      "price": "$3,000",
      "mrp": ""
    },
    {
      "popularity": "",
      "image": "https://www.specialized.com/us/en/s-works-aethos---dura-ace-di2/p/199439?color=321744-199439",
      "name": "S-Works Aethos - Dura-Ace Di2",
      "price": "$14,250",
      "mrp": ""
    },
    {
      "popularity": "",
      "image": "https://www.specialized.com/us/en/s-works-tarmac-sl7---sram-red-etap-axs/p/199464?color=321600-199464",
      "name": "S-Works Tarmac SL7 - SRAM Red eTap AXS",
      "price": "$14,000",
      "mrp": ""
    },
    {
      "popularity": "",
      "image": "https://www.specialized.com/us/en/s-works-tarmac-sl7---sram-red-etap-axs/p/216923?color=349978-216923",
      "name": "S-Works Tarmac SL7 - SRAM Red eTap AXS",
      "price": "$14,000",
      "mrp": ""
    }
  ]
}
